remo_gpu/__init__.py
remo_gpu/__main__.py
remo_gpu/cli.py
remo_gpu-0.1.3.dist-info/licenses/LICENSE
remo_gpu-0.1.3.dist-info/METADATA
remo_gpu-0.1.3.dist-info/WHEEL
remo_gpu-0.1.3.dist-info/entry_points.txt
remo_gpu-0.1.3.dist-info/top_level.txt
remo_gpu-0.1.3.dist-info/RECORD
