Metadata-Version: 2.4
Name: remo-gpu
Version: 0.1.3
Summary: Monitor GPUs on every SSH host defined in ~/.ssh/config.
Author: bobby
License: MIT License
Project-URL: Homepage, https://github.com/boyuaner/remo-gpu
Project-URL: Repository, https://github.com/boyuaner/remo-gpu
Keywords: gpu,ssh,monitoring,nvidia-smi
Classifier: Development Status :: 4 - Beta
Classifier: License :: OSI Approved :: MIT License
Classifier: Operating System :: OS Independent
Classifier: Programming Language :: Python
Classifier: Programming Language :: Python :: 3
Classifier: Programming Language :: Python :: 3.9
Classifier: Programming Language :: Python :: 3.10
Classifier: Programming Language :: Python :: 3.11
Classifier: Programming Language :: Python :: 3.12
Classifier: Environment :: Console
Classifier: Topic :: System :: Monitoring
Requires-Python: >=3.9
License-File: LICENSE
Requires-Dist: rich<14,>=13
Requires-Dist: textual<0.70,>=0.60
Dynamic: license-file
